plutolang/__init__.py
plutolang/queue.py
plutolang-0.0.1.dist-info/LICENSE
plutolang-0.0.1.dist-info/METADATA
plutolang-0.0.1.dist-info/WHEEL
plutolang-0.0.1.dist-info/top_level.txt
plutolang-0.0.1.dist-info/RECORD
