Metadata-Version: 2.1
Name: plutolang
Version: 0.0.1
Summary: The Client Library for Pluto Programming Language.
Project-URL: Homepage, https://github.com/pluto-lang/pluto
Project-URL: Issues, https://github.com/pluto-lang/pluto/issues
Classifier: Development Status :: 1 - Planning
Classifier: Environment :: Console
Classifier: Intended Audience :: Developers
Classifier: Natural Language :: English
Classifier: Programming Language :: Python :: 3
Classifier: Topic :: Software Development
Classifier: License :: OSI Approved :: Apache Software License
License-File: LICENSE
